list2term/__init__.py
list2term/list2term.py
list2term/multiprocessing.py
list2term-1.3.1.dist-info/licenses/LICENSE
list2term-1.3.1.dist-info/METADATA
list2term-1.3.1.dist-info/WHEEL
list2term-1.3.1.dist-info/top_level.txt
list2term-1.3.1.dist-info/RECORD
