Metadata-Version: 2.4
Name: list2term
Version: 1.3.1
Summary: A lightweight tool to mirror and dynamically update a Python list in your terminal, with built-in support for concurrent output (asyncio / threading / multiprocessing).
Author-email: Emilio Reyes <soda480@gmail.com>
Project-URL: Homepage, https://github.com/soda480/list2term
Classifier: Programming Language :: Python :: 3
Classifier: Operating System :: OS Independent
Requires-Python: >=3.9
License-File: LICENSE
Requires-Dist: colorama
Requires-Dist: cursor
Provides-Extra: dev
Requires-Dist: build; extra == "dev"
Requires-Dist: flake8; extra == "dev"
Requires-Dist: mock; extra == "dev"
Requires-Dist: radon; extra == "dev"
Requires-Dist: bandit; extra == "dev"
Requires-Dist: coverage; extra == "dev"
Requires-Dist: coverage-badge; extra == "dev"
Requires-Dist: twine; extra == "dev"
Dynamic: license-file
